{
  "version": "1.0.0",
  "updatedAt": "2026-04-23T00:00:00.000Z",
  "applications": [
    {
      "key": "hagicode",
      "displayName": "HagiCode",
      "kind": "application",
      "parentKey": null,
      "promoteId": "main-game-2026-04-29",
      "storeAppId": "4625540",
      "storeUrl": "https://store.steampowered.com/app/4625540/Hagicode/",
      "platformAppIds": {
        "windows": "4625541",
        "linux": "4625542",
        "macos": "4625543"
      }
    },
    {
      "key": "turbo-engine",
      "displayName": "Turbo Engine",
      "kind": "dlc",
      "parentKey": "hagicode",
      "storeAppId": "4635480",
      "storeUrl": "https://store.steampowered.com/app/4635480/Hagicode__Turbo_Engine/",
      "platformAppIds": {
        "windows": "4635480",
        "linux": "4635482",
        "macos": "4635481"
      }
    }
  ],
  "bundles": [
    {
      "key": "hagicode-plus",
      "displayName": "Hagicode Plus",
      "storeBundleId": "73989",
      "storeUrl": "https://store.steampowered.com/bundle/73989/Hagicode_Plus/",
      "includedApplicationKeys": [
        "hagicode",
        "turbo-engine"
      ]
    }
  ]
}
